devopspipelinepoc/__init__.py
devopspipelinepoc/main.py
devopspipelinepoc/data/data_output_worker.txt
devopspipelinepoc/data/path_output_worker.txt
devopspipelinepoc/data/scrapy_dockerfile.txt
devopspipelinepoc/data/selenium_dockerfile.txt
devopspipelinepoc/dockerfiles/__init__.py
devopspipelinepoc/dockerfiles/scrapy/__init__.py
devopspipelinepoc/dockerfiles/selenium/__init__.py
devopspipelinepoc/worker_files/__init__.py
devopspipelinepoc/worker_files/data_output/__init__.py
devopspipelinepoc/worker_files/data_output/worker.py
devopspipelinepoc/worker_files/path_output/__init__.py
devopspipelinepoc/worker_files/path_output/worker.py
devopspipelinepoc-0.1.7.dist-info/METADATA
devopspipelinepoc-0.1.7.dist-info/WHEEL
devopspipelinepoc-0.1.7.dist-info/entry_points.txt
devopspipelinepoc-0.1.7.dist-info/top_level.txt
devopspipelinepoc-0.1.7.dist-info/RECORD
